mb_pytorch/__init__.py
mb_pytorch/version.py
mb_pytorch/classification/__init__.py
mb_pytorch/classification/training.py
mb_pytorch/dataloader/__init__.py
mb_pytorch/dataloader/loader.py
mb_pytorch/dataloader/loader_old.py
mb_pytorch/detection/__init__.py
mb_pytorch/detection/training.py
mb_pytorch/metalearning/__init__.py
mb_pytorch/metalearning/meta_utils.py
mb_pytorch/metalearning/proto_dataloader.py
mb_pytorch/metalearning/prototypical.py
mb_pytorch/metrics/__init__.py
mb_pytorch/metrics/base.py
mb_pytorch/metrics/classification.py
mb_pytorch/metrics/detection.py
mb_pytorch/metrics/losses.py
mb_pytorch/metrics/segmentation.py
mb_pytorch/models/__init__.py
mb_pytorch/models/extra_models.py
mb_pytorch/models/lenet.py
mb_pytorch/models/modelloader.py
mb_pytorch/models/unet_models.py
mb_pytorch/models/blocks/__init__.py
mb_pytorch/models/blocks/attention_block.py
mb_pytorch/models/blocks/cnn.py
mb_pytorch/models/blocks/conv_block.py
mb_pytorch/models/blocks/conv_with_relu.py
mb_pytorch/models/blocks/model_out.py
mb_pytorch/models/blocks/rnn.py
mb_pytorch/segmentation/__init__.py
mb_pytorch/segmentation/training.py
mb_pytorch/training/__init__.py
mb_pytorch/training/accelerate_train.py
mb_pytorch/training/base_trainer.py
mb_pytorch/training/train_params.py
mb_pytorch/training/training.py
mb_pytorch/utils/__init__.py
mb_pytorch/utils/common.py
mb_pytorch/utils/compiler.py
mb_pytorch/utils/dist.py
mb_pytorch/utils/extra_utils.py
mb_pytorch/utils/generate_emb.py
mb_pytorch/utils/losses.py
mb_pytorch/utils/metrics.py
mb_pytorch/utils/model_utils.py
mb_pytorch/utils/viewer.py
mb_pytorch/utils/visualization.py
mb_pytorch/utils/yaml_reader.py
scripts/__init__.py
scripts/extra_utils/__init__.py
scripts/extra_utils/dataload_results.py
mb_pytorch-1.3.33.dist-info/METADATA
mb_pytorch-1.3.33.dist-info/WHEEL
mb_pytorch-1.3.33.dist-info/top_level.txt
mb_pytorch-1.3.33.dist-info/RECORD
