Metadata-Version: 2.1
Name: mb_pytorch
Version: 1.3.33
Summary: Pytorch functions
Author: ['Malav Bateriwala']
Requires-Python: >=3.8
Requires-Dist: mb_base
Requires-Dist: mb_utils
Requires-Dist: mb_pandas
